README.txt
setup.py
jiote/__init__.py
jiote.egg-info/PKG-INFO
jiote.egg-info/SOURCES.txt
jiote.egg-info/dependency_links.txt
jiote.egg-info/not-zip-safe
jiote.egg-info/top_level.txt
jiote/models/__init__.py
jiote/models/device.py
jiote/models/gps.py