Metadata-Version: 1.0
Name: jiote
Version: 0.1.4
Summary: IOT abstraction
Home-page: https://github.com/gamikun/jiote
Author: Gamaliel Espinoza Macedo
Author-email: gamaliel.espinoza@gmail.com
License: UNKNOWN
Platform: UNKNOWN
